{
  "sections": {
    "4bc97fd9-8b39-4479-9234-8b04cd49088e": {
      "type": "product-collection",
      "blocks": {
        "template--21009528586518__4bc97fd9-8b39-4479-9234-8b04cd49088e-section_padding-1": {
          "type": "section_padding",
          "settings": {
            "section_padding_top": 0,
            "section_padding_bottom": 100,
            "section_padding_top_md": 0,
            "section_padding_bottom_md": 80,
            "section_padding_top_xs": 0,
            "section_padding_bottom_xs": 60
          }
        }
      },
      "block_order": [
        "template--21009528586518__4bc97fd9-8b39-4479-9234-8b04cd49088e-section_padding-1"
      ],
      "settings": {
        "title": "Product Collection",
        "btn-label": "",
        "product_collection": "etrade-products",
        "number_of_products_to_show": 4,
        "product_layout": "1",
        "excluded_products": [

        ],
        "sort_by": "title",
        "reverse_order": false,
        "hover_img": false
      }
    },
    "006b98e5-f543-41c3-ac5e-4cd8bc26ade3": {
      "type": "newsletter",
      "blocks": {
        "e03928ff-1869-4aeb-8cb6-e56daddd384c": {
          "type": "section_padding",
          "settings": {
            "section_padding_top": 0,
            "section_padding_bottom": 100,
            "section_padding_top_md": 0,
            "section_padding_bottom_md": 80,
            "section_padding_top_xs": 0,
            "section_padding_bottom_xs": 60
          }
        }
      },
      "block_order": [
        "e03928ff-1869-4aeb-8cb6-e56daddd384c"
      ],
      "settings": {
        "before_title_icon": "fas fa-envelope-open",
        "before_title_text": "Newsletter",
        "before_title_color": "#3577f0",
        "title": "Get weekly update",
        "bg_img": "shopify:\/\/shop_images\/bg-image-5.jpg",
        "form_action_url": "https:\/\/axilweb.us21.list-manage.com\/subscribe\/post?u=d2a79986af90d180038dc91c6&amp;id=e71e328c72&amp;f_id=0015dce6f0"
      }
    }
  },
  "order": [
    "4bc97fd9-8b39-4479-9234-8b04cd49088e",
    "006b98e5-f543-41c3-ac5e-4cd8bc26ade3"
  ]
}
